withings/__init__.py
withings/api.py
withings/codes.py
withings/exceptions.py
withings/status_codes.py
withings/structures.py
withings/oauth2/__init__.py
withings/oauth2/authorizer.py
withings/oauth2/callback.py
withings/oauth2/parser.py
python_withings-1.0.31.dist-info/METADATA
python_withings-1.0.31.dist-info/WHEEL
python_withings-1.0.31.dist-info/top_level.txt
python_withings-1.0.31.dist-info/RECORD
