Metadata-Version: 2.1
Name: python-withings
Version: 1.0.31
Summary: Wrapper package for Withings API
Home-page: https://github.com/strohganoff/python-withings
License: UNKNOWN
Platform: UNKNOWN
Requires-Dist: requests-oauthlib
Requires-Dist: python-dateutil
